shopkeeper_calculate_mcp_server/__init__.py
shopkeeper_calculate_mcp_server-0.1.0.dist-info/METADATA
shopkeeper_calculate_mcp_server-0.1.0.dist-info/WHEEL
shopkeeper_calculate_mcp_server-0.1.0.dist-info/entry_points.txt
shopkeeper_calculate_mcp_server-0.1.0.dist-info/RECORD
